planparser/__init__.py
planparser/cli.py
planparser/planparser.py
planparser-0.1.0b0.dist-info/entry_points.txt
planparser-0.1.0b0.dist-info/LICENSE
planparser-0.1.0b0.dist-info/WHEEL
planparser-0.1.0b0.dist-info/METADATA
planparser-0.1.0b0.dist-info/RECORD
